triesus/__init__.py
triesus/cli.py
triesus/cover_set.py
triesus/input.py
triesus/naive_sus.py
triesus/random.py
triesus/run_naive_sus.py
triesus/run_triesus.py
triesus/trie.py
triesus/trienode.py
triesus/triesus.py
triesus/assets/benchmark.png
triesus/assets/benchmark.svg
triesus/assets/triesus_logo.png
triesus-0.6.1.dist-info/LICENCE
triesus-0.6.1.dist-info/METADATA
triesus-0.6.1.dist-info/WHEEL
triesus-0.6.1.dist-info/entry_points.txt
triesus-0.6.1.dist-info/top_level.txt
triesus-0.6.1.dist-info/RECORD
