Metadata-Version: 2.2
Name: triesus
Version: 0.6.1
Summary: Find the Smallest Unique Subset (SUS), fast
Author-email: Alessandro Lussana <alessandro.lussana@proton.me>
Maintainer-email: Alessandro Lussana <alessandro.lussana@proton.me>
Project-URL: Homepage, https://github.com/alussana/TrieSUS
Project-URL: Bug Tracker, https://github.com/alussana/TrieSUS/issues
Project-URL: Source, https://github.com/alussana/TrieSUS/
Keywords: sets,algorithm,trie,cli
Classifier: Programming Language :: Python :: 3
Classifier: License :: OSI Approved :: MIT License
Classifier: Operating System :: OS Independent
Requires-Python: >=3.7
License-File: LICENCE
Requires-Dist: importlib-metadata; python_version > "3.7"
Requires-Dist: ortools>9.7
